auto_gpt_vicuna/__init__.py
auto_gpt_vicuna-0.0.1.dist-info/METADATA
auto_gpt_vicuna-0.0.1.dist-info/WHEEL
auto_gpt_vicuna-0.0.1.dist-info/licenses/LICENSE
auto_gpt_vicuna-0.0.1.dist-info/RECORD
